Metadata-Version: 2.1
Name: torch-multilabel-embedding
Version: 0.1.0
Summary: Training of multi-label embeddings for k-shingled input sequences
Home-page: http://github.com/ulf1/torch-multilabel-embedding
Author: Ulf Hamster
Author-email: 554c46@gmail.com
License: Apache License 2.0
Platform: UNKNOWN
Requires-Python: >=3.6
License-File: LICENSE
